[
  {
    "id": "df7b077e6f65d139",
    "title": "Colorado house by Studio B and Studio Brother John appears to \"hover over the land\"",
    "url": "https://www.dezeen.com/2026/07/14/9631-mountain-ridge-place-studio-b-studio-brother-john-boulder-colorado/",
    "source_name": "Dezeen",
    "source_type": "fixed_rss",
    "categories": [
      "architecture_interior",
      "sustainable_material"
    ],
    "summary": "Local outfit Studio Brother John has collaborated with Studio B Architecture + Interiors for a house in Boulder, Colorado, USA making the most of its mountainous site and replacing a structure destroy…",
    "thumbnail_url": "http://static.dezeen.com/uploads/2026/07/9631-mountain-ridge-place-boulder-colorado-studio-b-studio-brother-john-sq_dezeen_2364_col_0-411x411.jpg",
    "published_at": "2026-07-14T19:14:37+09:00",
    "fetched_at": "2026-07-20T16:47:49.931425+09:00",
    "matched_keywords": []
  },
  {
    "id": "6053973cbfe10d9d",
    "title": "Dezeen debate features \"refuge for the uncreative\"",
    "url": "https://www.dezeen.com/2026/07/14/david-chipperfield-faro-santander-dezeen-debate/",
    "source_name": "Dezeen",
    "source_type": "fixed_rss",
    "categories": [
      "architecture_interior",
      "sustainable_material"
    ],
    "summary": "The latest Dezeen Debate newsletter features the transformation of a historic Spanish bank into the Faro Santander museum by David Chipperfield Architects. Subscribe to Dezeen Debate now. Scheduled to…",
    "thumbnail_url": "http://static.dezeen.com/uploads/2026/07/faro-santander-david-chipperfield-architecture-cultural-museums-art-galleries-spain_dezeen_2364_col_6_square-411x411.jpg",
    "published_at": "2026-07-14T18:00:46+09:00",
    "fetched_at": "2026-07-20T16:47:49.931449+09:00",
    "matched_keywords": []
  },
  {
    "id": "3f0e6096a72a485c",
    "title": "Play-Doh enters \"home decor space\" with flower-making kit for adults",
    "url": "https://www.dezeen.com/2026/07/14/play-doh-blooms-flower-making-kit/",
    "source_name": "Dezeen",
    "source_type": "fixed_rss",
    "categories": [
      "architecture_interior",
      "sustainable_material"
    ],
    "summary": "Toy company Hasbro has announced a line of Play-Doh products for adults with the release of Blooms, a flower-making kit for creating \"lifelike flowers\" that can be coated with a finishing spray for pr…",
    "thumbnail_url": "http://static.dezeen.com/uploads/2026/07/iplay-doh-blooms-kit_dezeen_sq-22364_col_2-1-411x411.jpg",
    "published_at": "2026-07-14T17:00:48+09:00",
    "fetched_at": "2026-07-20T16:47:49.931473+09:00",
    "matched_keywords": []
  },
  {
    "id": "b5ea70e1a98a6e06",
    "title": "Heavily stylistic approach to stadium design \"should die down\" says Populous global director Jonathan Mallie",
    "url": "https://www.dezeen.com/2026/07/14/jonathan-mallie-populous-interview-future-stadium/",
    "source_name": "Dezeen",
    "source_type": "fixed_rss",
    "categories": [
      "architecture_interior",
      "sustainable_material"
    ],
    "summary": "Continuing our Future Stadium series, we interview architect Jonathan Mallie about the combination of urban planning, computational design and economics behind Populous, the studio driving global stad…",
    "thumbnail_url": "http://static.dezeen.com/uploads/2026/07/Jonathan-Mallie_Headshot-sq1-411x411.jpg",
    "published_at": "2026-07-14T14:30:43+09:00",
    "fetched_at": "2026-07-20T16:47:49.931497+09:00",
    "matched_keywords": []
  },
  {
    "id": "2e3ee03989b12d59",
    "title": "Essence tiles by Casalgrande Padana",
    "url": "https://www.dezeen.com/2026/07/14/essence-tiles-casalgrande-padana-dezeen-showroom/",
    "source_name": "Dezeen",
    "source_type": "fixed_rss",
    "categories": [
      "architecture_interior",
      "sustainable_material"
    ],
    "summary": "Dezeen Showroom: Italian brand Casalgrande Padana has created an ode to larch wood with its Essence porcelain stoneware tiles, part of the Elements collection. Essence tiles combine the rich grain and…",
    "thumbnail_url": "http://static.dezeen.com/uploads/2026/07/essence-tiles-casalgrande-padana-design_dezeen_2364_sq-411x411.jpg",
    "published_at": "2026-07-14T13:00:33+09:00",
    "fetched_at": "2026-07-20T16:47:49.931520+09:00",
    "matched_keywords": []
  },
  {
    "id": "a833ba8054eec638",
    "title": "Tom Kneepkens \"integrates living and nature\" at Dutch forest villa",
    "url": "https://www.dezeen.com/2026/07/14/tom-kneepkens-forest-villa-home-netherlands/",
    "source_name": "Dezeen",
    "source_type": "fixed_rss",
    "categories": [
      "architecture_interior",
      "sustainable_material"
    ],
    "summary": "Local architect Tom Kneepkens has completed Forest Villa MB, a home in the Netherlands sheltered by a gridded timber roof with openings to accommodate the surrounding trees. Nestled in a forested site…",
    "thumbnail_url": "http://static.dezeen.com/uploads/2026/06/tom-kneepkens-forest-villa-home-netherlands-sq_dezeen_2364_col_0-411x411.jpg",
    "published_at": "2026-07-14T10:45:16+09:00",
    "fetched_at": "2026-07-20T16:47:49.931543+09:00",
    "matched_keywords": []
  },
  {
    "id": "712dbee1e1703ea7",
    "title": "万博の落合陽一パビリオン「null2（ヌルヌル）」横浜に転生。「null2n」「null4」はどんな施設？ 3つの違いを解説 - トラベル Watch",
    "url": "https://news.google.com/rss/articles/CBMiaEFVX3lxTFBTMUxWSEtyNDZuZkdSZ2NvcmgzVlViY1M0MzJYbi1xZ2RRVXRQV2pGS0xiY256NG96bFVBN09qWFVjWVBWUEdpZnVaUldJRFA1VTIzUmtQWUp5SjlYWk9fSXdIYVhaYVk5?oc=5",
    "source_name": "トラベル Watch",
    "source_type": "keyword_search",
    "categories": [
      "exhibition_expo"
    ],
    "summary": "万博の落合陽一パビリオン「null2（ヌルヌル）」横浜に転生。「null2n」「null4」はどんな施設？ 3つの違いを解説 トラベル Watch",
    "thumbnail_url": null,
    "published_at": "2026-07-14T09:36:16+09:00",
    "fetched_at": "2026-07-20T16:47:50.880259+09:00",
    "matched_keywords": [
      "万博 パビリオン"
    ]
  },
  {
    "id": "746f9b53036d770e",
    "title": "Nokia unveils nostalgic dumbphones with dedicated AI button",
    "url": "https://www.dezeen.com/2026/07/14/nokia-unveils-nostalgic-dumbphones-with-dedicated-ai-button/",
    "source_name": "Dezeen",
    "source_type": "fixed_rss",
    "categories": [
      "architecture_interior",
      "sustainable_material"
    ],
    "summary": "Tech company HMD has launched a range of retro Nokia brick phones with limited internet capabilities and an AI assistant button integrated into the centre of the keypad. Like many dumbphones, these 4G…",
    "thumbnail_url": "http://static.dezeen.com/uploads/2026/07/sq-nokia-4g-feature-phones_dezeen_2364_col_0-411x411.jpg",
    "published_at": "2026-07-14T09:00:06+09:00",
    "fetched_at": "2026-07-20T16:47:49.931565+09:00",
    "matched_keywords": []
  },
  {
    "id": "4e5ce21dea32e886",
    "title": "ペン先・インク交換に対応した「コピック マルチライナープラス」発売。くり返し使えるドローイングペン",
    "url": "https://www.axismag.jp/posts/2026/07/717049.html",
    "source_name": "AXIS",
    "source_type": "fixed_rss",
    "categories": [
      "space_design",
      "architecture_interior"
    ],
    "summary": "画材ブランド「コピック」を展開するトゥーマーカープロダクツは、新製品「コピック マルチライナープラス」を、7月17日（金）より一般発売する。同製品は、従来の「コピック マルチライナー」の特徴を受け継ぎながら、ペン先の摩耗 […]",
    "thumbnail_url": null,
    "published_at": "2026-07-14T08:28:52+09:00",
    "fetched_at": "2026-07-20T16:47:48.562294+09:00",
    "matched_keywords": []
  },
  {
    "id": "c7fc740d1d3a5d02",
    "title": "万博のあの体験、ついに東京へ。石黒浩プロデュース「いのちの未来＋」7月25日開幕 落合陽一氏をゲストに迎えトークショーも実施！ - PR TIMES",
    "url": "https://news.google.com/rss/articles/CBMiakFVX3lxTE5fUlhCU2hVTnRra0FmZUgycEpibnFtQTRVLXR0bGhodWhmYWlWak5qVHdFN0xxTFgzRHlqdVl0dFdzMW1Bakl4NUJrckR0ZnlLdmZRUGtXVnNyV0pjYUdXZXcxTTN2VnVIRFE?oc=5",
    "source_name": "PR TIMES",
    "source_type": "keyword_search",
    "categories": [
      "exhibition_expo"
    ],
    "summary": "万博のあの体験、ついに東京へ。石黒浩プロデュース「いのちの未来＋」7月25日開幕 落合陽一氏をゲストに迎えトークショーも実施！ PR TIMES",
    "thumbnail_url": null,
    "published_at": "2026-07-14T08:01:09+09:00",
    "fetched_at": "2026-07-20T16:47:50.880082+09:00",
    "matched_keywords": [
      "万博 パビリオン"
    ]
  },
  {
    "id": "adda5ed301e0b7f5",
    "title": "万博の落合陽一パビリオン『null2』が“転生”へ…詳細情報が発表 横浜で常設、チケット価格など公開【詳細】 【大阪・関西万博】 - オリコンニュース",
    "url": "https://news.google.com/rss/articles/CBMiVkFVX3lxTE5jYVdmaFM2UVlzR3hhOUVpRVJVWWh4eEhJNUI0Z0d5Yi1fMUgxQkpIakJRc2xta0prTWFqMnpZT1ZpTGdVdGlTemwyNlJKSmZkQTlUYmV3?oc=5",
    "source_name": "オリコンニュース",
    "source_type": "keyword_search",
    "categories": [
      "exhibition_expo"
    ],
    "summary": "万博の落合陽一パビリオン『null2』が“転生”へ…詳細情報が発表 横浜で常設、チケット価格など公開【詳細】 【大阪・関西万博】 オリコンニュース",
    "thumbnail_url": null,
    "published_at": "2026-07-14T07:10:00+09:00",
    "fetched_at": "2026-07-20T16:47:50.880415+09:00",
    "matched_keywords": [
      "万博 パビリオン"
    ]
  },
  {
    "id": "34dbeb0a6847fd3a",
    "title": "Neri&Hu wraps Hong Kong hotel in \"urban tapestry\" facade",
    "url": "https://www.dezeen.com/2026/07/14/nerihu-mandarin-oriental-the-landmark-facade-hong-kong/",
    "source_name": "Dezeen",
    "source_type": "fixed_rss",
    "categories": [
      "architecture_interior",
      "sustainable_material"
    ],
    "summary": "Architecture studio Neri&Hu has upgraded the facade of Mandarin Oriental The Landmark in Hong Kong, using staggered terracotta tiles to resemble a piece of woven tapestry. Located on Queen's Road in H…",
    "thumbnail_url": "http://static.dezeen.com/uploads/2026/07/nerihu-mandarin-oriental-the-landmark-hotel-facade-hong-kong_dezeen_2364_col_sq-411x411.jpg",
    "published_at": "2026-07-14T07:00:42+09:00",
    "fetched_at": "2026-07-20T16:47:49.931591+09:00",
    "matched_keywords": []
  },
  {
    "id": "40de4985a8aa1eb4",
    "title": "落合陽一氏の大阪・関西万博パビリオン「null²（ﾇﾙﾇﾙ）」が常設シアターに！横浜にオープン｜レッツエンジョイ東京 - レッツエンジョイ東京",
    "url": "https://news.google.com/rss/articles/CBMiT0FVX3lxTE51MTRQMkstVGtVSFBvaEtMTVlFRWZzd1h2aTY2dzNtUFQ0eVdwdk5YblZ3QmpncnJ2ZzFVSHc2QklpVFFVcjNYNDRDb2hzNUU?oc=5",
    "source_name": "レッツエンジョイ東京",
    "source_type": "keyword_search",
    "categories": [
      "exhibition_expo"
    ],
    "summary": "落合陽一氏の大阪・関西万博パビリオン「null²（ﾇﾙﾇﾙ）」が常設シアターに！横浜にオープン｜レッツエンジョイ東京 レッツエンジョイ東京",
    "thumbnail_url": null,
    "published_at": "2026-07-14T07:00:00+09:00",
    "fetched_at": "2026-07-20T16:47:50.880114+09:00",
    "matched_keywords": [
      "万博 パビリオン"
    ]
  },
  {
    "id": "bc91092e657727eb",
    "title": "【破産手続開始】店舗デザインの受注から施工まで一手に担っていた『アートプロポーション』工事部門の大幅減少もあって資金繰りが困難に 新潟市南区 - TBS NEWS DIG",
    "url": "https://news.google.com/rss/articles/CBMiZ0FVX3lxTE5FdVdhZzhOTlc0ZHVRWm5wWjRBQ0ZyM3dZa096MjRGdEsybmptVUdVNjdwVzlMSk9XQUdZZHZJdGpucGFFazlaUldHXzkwT0RtS005eDF4SllvdFEzZl9aaWlkWEluYlU?oc=5",
    "source_name": "TBS NEWS DIG",
    "source_type": "keyword_search",
    "categories": [
      "space_design",
      "architecture_interior"
    ],
    "summary": "【破産手続開始】店舗デザインの受注から施工まで一手に担っていた『アートプロポーション』工事部門の大幅減少もあって資金繰りが困難に 新潟市南区 TBS NEWS DIG",
    "thumbnail_url": null,
    "published_at": "2026-07-14T05:31:00+09:00",
    "fetched_at": "2026-07-20T16:47:50.575511+09:00",
    "matched_keywords": [
      "商業施設 デザイン"
    ]
  },
  {
    "id": "69941a9f0baa7c81",
    "title": "業界横断で持続可能な空間づくり目指す共創基盤発足 丹青社 | 産業別動向記事 | プレミアム - nikkinonline.com",
    "url": "https://news.google.com/rss/articles/CBMiZEFVX3lxTE11RS1BNDZiNzJSbldPMUxSdnNhT3JmTzNlajZqanFwT1ltLWZsUFFOazN0NGViMERINmdGVWRxTTZlczFVRGk1UnVMcjZabmlVMjVidWxYV1NkTnIyd1hhZnhuWlk?oc=5",
    "source_name": "nikkinonline.com",
    "source_type": "keyword_search",
    "categories": [
      "space_design"
    ],
    "summary": "業界横断で持続可能な空間づくり目指す共創基盤発足 丹青社 | 産業別動向記事 | プレミアム nikkinonline.com",
    "thumbnail_url": null,
    "published_at": "2026-07-14T02:20:14+09:00",
    "fetched_at": "2026-07-20T16:47:50.346144+09:00",
    "matched_keywords": [
      "丹青社"
    ]
  },
  {
    "id": "f8fbbc328bbe059f",
    "title": "横浜グリーンエクスポの前哨戦！「null²ⁿ」10月14日グランドオープン決定・チケット一般販売スタート！ - PR TIMES",
    "url": "https://news.google.com/rss/articles/CBMiakFVX3lxTE9Ra1lNanFzbDQ4VXBkYzJUcXRTWVVmZUxDUlJ1RnNDN0gxSG9HWm1ZYnRTRlcySFl1QzlwYU9abHBsNlUtVXp5cURSV0t3MlFncWVSUE1LQUhRak1BamlObzduZjRVRkhTZUE?oc=5",
    "source_name": "PR TIMES",
    "source_type": "keyword_search",
    "categories": [
      "exhibition_expo"
    ],
    "summary": "横浜グリーンエクスポの前哨戦！「null²ⁿ」10月14日グランドオープン決定・チケット一般販売スタート！ PR TIMES",
    "thumbnail_url": null,
    "published_at": "2026-07-14T02:20:11+09:00",
    "fetched_at": "2026-07-20T16:47:50.880229+09:00",
    "matched_keywords": [
      "万博 パビリオン"
    ]
  },
  {
    "id": "8ec6c4a4e342ff45",
    "title": "専用施設型産後ケアホテル「Villa Mom」東京・有明が6月22日（月）開業｜乃村工藝社はデザイン・設計と施工、サービスコンセプトを担当 - 北海道新聞デジタル",
    "url": "https://news.google.com/rss/articles/CBMiiAFBVV95cUxOVGdsQWJ6SDNIRnB1eEYtOTIwV3ZxbC1acFRkLXBYWXJQQkFoWGMzTHF6bXZOSWl4b01HQk83LUxNVFJMWFdaNHAyakg4SlVrNjBWY0JUcVJqLU5mcW5NYkE2N09WY2R5a3RkMlpwTHRfMjIxUGJwV1JyclVXbVhweEg1bENxOC1N?oc=5",
    "source_name": "北海道新聞デジタル",
    "source_type": "keyword_search",
    "categories": [
      "space_design"
    ],
    "summary": "専用施設型産後ケアホテル「Villa Mom」東京・有明が6月22日（月）開業｜乃村工藝社はデザイン・設計と施工、サービスコンセプトを担当 北海道新聞デジタル",
    "thumbnail_url": null,
    "published_at": "2026-07-14T00:18:14+09:00",
    "fetched_at": "2026-07-20T16:47:50.256753+09:00",
    "matched_keywords": [
      "乃村工藝社"
    ]
  }
]
